translation_canvas/__init__.py
translation_canvas/app.py
translation_canvas/cli.py
translation_canvas/eval.py
translation_canvas/evaluate_without_instructscore.py
translation_canvas/file_to_json.py
translation_canvas/help_text.json
translation_canvas/plotly_functions.py
translation_canvas/readwrite_database.py
translation_canvas/setup.py
translation_canvas/spawn_eval_and_monitor.py
translation_canvas/sql_queries.py
translation_canvas/utils.py
translation_canvas/InstructScore_SEScore3/InstructScore.py
translation_canvas/InstructScore_SEScore3/code/compute_feedback_score.py
translation_canvas/InstructScore_SEScore3/code/construct_wmt20.py
translation_canvas/InstructScore_SEScore3/code/debug_padding.py
translation_canvas/InstructScore_SEScore3/code/finetune_llama.py
translation_canvas/InstructScore_SEScore3/code/merge_files.py
translation_canvas/InstructScore_SEScore3/code/output_results.py
translation_canvas/InstructScore_SEScore3/code/output_reward.py
translation_canvas/InstructScore_SEScore3/code/post_process_gpt4_feedback.py
translation_canvas/InstructScore_SEScore3/code/post_process_inference.py
translation_canvas/InstructScore_SEScore3/code/prepare_gpt4_critics.py
translation_canvas/InstructScore_SEScore3/code/prepare_mt_data.py
translation_canvas/InstructScore_SEScore3/code/preprocess_sample_data.py
translation_canvas/InstructScore_SEScore3/code/process_result_webnlg.py
translation_canvas/InstructScore_SEScore3/code/reward_modeling.py
translation_canvas/InstructScore_SEScore3/code/simple_format.py
translation_canvas/InstructScore_SEScore3/code/test_llama.py
translation_canvas/InstructScore_SEScore3/code/test_webnlg.py
translation_canvas/InstructScore_SEScore3/code/train.py
translation_canvas/InstructScore_SEScore3/reproduce/process_result_bagel.py
translation_canvas/InstructScore_SEScore3/reproduce/process_result_caption.py
translation_canvas/InstructScore_SEScore3/reproduce/process_result_commongen.py
translation_canvas-1.0.2.dist-info/LICENSE
translation_canvas-1.0.2.dist-info/METADATA
translation_canvas-1.0.2.dist-info/WHEEL
translation_canvas-1.0.2.dist-info/entry_points.txt
translation_canvas-1.0.2.dist-info/top_level.txt
translation_canvas-1.0.2.dist-info/RECORD
